odoo9_addon_partner_contact_nutrition_goal-9.0.1.0.0-py2.7-nspkg.pth
odoo_addons/partner_contact_nutrition_goal/__openerp__.py
odoo_addons/partner_contact_nutrition_goal/__init__.py
odoo_addons/partner_contact_nutrition_goal/README.rst
odoo_addons/partner_contact_nutrition_goal/models/res_partner.py
odoo_addons/partner_contact_nutrition_goal/models/__init__.py
odoo_addons/partner_contact_nutrition_goal/views/res_partner_view.xml
odoo_addons/partner_contact_nutrition_goal/static/description/icon.png
odoo9_addon_partner_contact_nutrition_goal-9.0.1.0.0.dist-info/top_level.txt
odoo9_addon_partner_contact_nutrition_goal-9.0.1.0.0.dist-info/WHEEL
odoo9_addon_partner_contact_nutrition_goal-9.0.1.0.0.dist-info/RECORD
odoo9_addon_partner_contact_nutrition_goal-9.0.1.0.0.dist-info/metadata.json
odoo9_addon_partner_contact_nutrition_goal-9.0.1.0.0.dist-info/DESCRIPTION.rst
odoo9_addon_partner_contact_nutrition_goal-9.0.1.0.0.dist-info/METADATA
odoo9_addon_partner_contact_nutrition_goal-9.0.1.0.0.dist-info/namespace_packages.txt
